napari_vascilia/Napari_VASCilia_v1_4_0.py
napari_vascilia/__init__.py
napari_vascilia/napari.yaml
napari_vascilia/ui_setup.py
napari_vascilia/_tests/__init__.py
napari_vascilia/assets/VASCilia_logo1.png
napari_vascilia/core/Process_multiple_stacks.py
napari_vascilia/core/VASCilia_utils.py
napari_vascilia/core/__init__.py
napari_vascilia/core/batch_action.py
napari_vascilia/core/calculate_distance.py
napari_vascilia/core/calculate_measurements.py
napari_vascilia/core/combine_labels.py
napari_vascilia/core/commute_training_action.py
napari_vascilia/core/compute_orientation_action.py
napari_vascilia/core/compute_signal_action.py
napari_vascilia/core/delete_action.py
napari_vascilia/core/identify_celltype_action.py
napari_vascilia/core/open_cochlea_action.py
napari_vascilia/core/predict_tonotopic_region.py
napari_vascilia/core/prepare_length_json.py
napari_vascilia/core/reset_exit_action.py
napari_vascilia/core/rotate_AI.py
napari_vascilia/core/rotate_cochlea_action.py
napari_vascilia/core/save_distance.py
napari_vascilia/core/segment_cochlea_action.py
napari_vascilia/core/trim_AI.py
napari_vascilia/core/trim_cochlea_action.py
napari_vascilia/core/upload_cochlea_action.py
napari_vascilia/core/visualize_track_action.py
napari_vascilia-1.4.0.dist-info/licenses/LICENSE
napari_vascilia-1.4.0.dist-info/METADATA
napari_vascilia-1.4.0.dist-info/WHEEL
napari_vascilia-1.4.0.dist-info/entry_points.txt
napari_vascilia-1.4.0.dist-info/top_level.txt
napari_vascilia-1.4.0.dist-info/RECORD
