Metadata-Version: 2.4
Name: napari-vascilia
Version: 1.4.0
Summary: A plugin for deep learning-based 3D analysis of cochlear hair cell stereocilia bundles.
Home-page: https://github.com/ucsdmanorlab/Napari-VASCilia
Author: Yasmin Kassim
Author-email: ymkgz8@mail.missouri.edu
License: BSD-3-Clause
Classifier: Programming Language :: Python :: 3
Classifier: License :: OSI Approved :: BSD License
Classifier: Operating System :: OS Independent
Classifier: Framework :: napari
License-File: LICENSE
Requires-Dist: numpy==1.26.4
Requires-Dist: scikit-learn==1.3.2
Requires-Dist: opencv-python
Requires-Dist: matplotlib
Requires-Dist: imagecodecs
Requires-Dist: tifffile
Requires-Dist: napari[all]
Requires-Dist: readlif
Requires-Dist: czitools==0.4.1
Requires-Dist: npe2
Requires-Dist: colormap==1.1.0
Requires-Dist: segmentation-models-pytorch==0.3.3
Requires-Dist: pretrainedmodels==0.7.4
Dynamic: author
Dynamic: author-email
Dynamic: classifier
Dynamic: description
Dynamic: description-content-type
Dynamic: home-page
Dynamic: license
Dynamic: license-file
Dynamic: requires-dist
Dynamic: summary
